{
    "Melee": [
        {"name": "Basic Sword", "type": "Melee", "damage": 5, "element": null, "Cost": 8, "Durability": 25, "special_ability": null},
        {"name": "Basic Axe", "type": "Melee", "damage": 6, "element": null, "Cost": 9, "Durability": 20, "special_ability": null},
        {"name": "Basic Dagger", "type": "Melee", "damage": 4, "element": null, "Cost": 7, "Durability": 15, "special_ability": null},
        {"name": "Basic Spear", "type": "Melee", "damage": 5, "element": null, "Cost": 8, "Durability": 20, "special_ability": null},
        {"name": "Steel Sword", "type": "Melee", "damage": 12, "element": null, "Cost": 15, "Durability": 50, "special_ability": null},
        {"name": "Steel Axe", "type": "Melee", "damage": 13, "element": null, "Cost": 16, "Durability": 45, "special_ability": null},
        {"name": "Steel Dagger", "type": "Melee", "damage": 10, "element": null, "Cost": 13, "Durability": 40, "special_ability": null},
        {"name": "Steel Spear", "type": "Melee", "damage": 11, "element": null, "Cost": 14, "Durability": 45, "special_ability": null},
        {"name": "Iron Sword", "type": "Melee", "damage": 18, "element": null, "Cost": 25, "Durability": 60, "special_ability": null},
        {"name": "Iron Axe", "type": "Melee", "damage": 19, "element": null, "Cost": 27, "Durability": 55, "special_ability": null},
        {"name": "Iron Dagger", "type": "Melee", "damage": 17, "element": null, "Cost": 22, "Durability": 50, "special_ability": null},
        {"name": "Iron Spear", "type": "Melee", "damage": 18, "element": null, "Cost": 25, "Durability": 55, "special_ability": null},
        {"name":  "Gold Sword", "type": "Melee", "damage": 24, "element": null, "Cost": 35, "Durability": 70, "special_ability": null},
        {"name":  "Gold Axe", "type": "Melee", "damage": 26, "element": null, "Cost": 38, "Durability": 65, "special_ability": null},
        {"name":  "Gold Dagger", "type": "Melee", "damage": 22, "element": null, "Cost": 30, "Durability": 60, "special_ability": null},
        {"name":  "Gold Spear", "type": "Melee", "damage": 24, "element": null, "Cost": 35, "Durability": 65, "special_ability": null},
        {"name": "Titanium Sword", "type": "Melee", "damage": 25, "element": null, "Cost": 40, "Durability": 70, "special_ability": null},
        {"name": "Titanium Dagger", "type": "Melee", "damage": 25, "element": null, "Cost": 40, "Durability": 70, "special_ability": null},
        {"name": "Titanium Axe", "type": "Melee", "damage": 30, "element": null, "Cost": 50, "Durability": 80, "special_ability": null},
        {"name": "Titanium Spear", "type": "Melee", "damage": 32, "element": null, "Cost": 55, "Durability": 85, "special_ability": null},
        {"name": "Celestial Sword", "type": "Melee", "damage": 38, "element": null, "Cost": 60, "Durability": 90, "special_ability": null},
        {"name": "Celestial Axe", "type": "Melee", "damage": 40, "element": null, "Cost": 65, "Durability": 95, "special_ability": null},
        {"name": "Celestial Dagger", "type": "Melee", "damage": 30, "element": null, "Cost": 45, "Durability": 80, "special_ability": null},
        {"name": "Celestial Spear", "type": "Melee", "damage": 42, "element": null, "Cost": 70, "Durability": 100, "special_ability": null},
        {"name": "Dragon Bone Sword", "type": "Melee", "damage": 60, "element": null, "Cost": 100, "Durability": 150, "special_ability": null},
        {"name": "Dragon Bone Axe", "type": "Melee", "damage": 65, "element": null, "Cost": 110, "Durability": 150, "special_ability": null},
        {"name": "Dragon Bone Dagger", "type": "Melee", "damage": 55, "element": null, "Cost": 95, "Durability": 140, "special_ability": null},
        {"name": "Dragon Bone Spear", "type": "Melee", "damage": 70, "element": null, "Cost": 120, "Durability": 160, "special_ability": null}
    ],

    "Ranged": [
        {"name": "Basic Bow", "type": "Ranged", "damage": 6, "element": null, "Cost": 10, "Durability": 30, "special_ability": null},
        {"name": "Basic Crossbow", "type": "Ranged", "damage": 8, "element": null, "Cost": 12, "Durability": 35, "special_ability": null},
        {"name": "Slingshot", "type": "Ranged", "damage": 4, "element": null, "Cost": 5, "Durability": 15, "special_ability": null},
        {"name": "Long Bow", "type": "Ranged", "damage": 28, "element": null, "Cost": 40, "Durability": 50, "special_ability": null},
        {"name": "Heavy Crossbow", "type": "Ranged", "damage": 32, "element": null, "Cost": 50, "Durability": 60, "special_ability": null},
        {"name": "Composite Bow", "type": "Ranged", "damage": 16, "element": null, "Cost": 25, "Durability": 40, "special_ability": null},
        {"name": "Recurve Bow", "type": "Ranged", "damage": 18, "element": null, "Cost": 30, "Durability": 45, "special_ability": null},
        {"name": "Rapid Crossbow", "type": "Ranged", "damage": 24, "element": null, "Cost": 40, "Durability": 50, "special_ability": null},
        {"name": "Magnum Crossbow", "type": "Ranged", "damage": 35, "element": null, "Cost": 60, "Durability": 70, "special_ability": null},
        {"name": "Hunter's Bow", "type": "Ranged", "damage": 30, "element": null, "Cost": 50, "Durability": 65, "special_ability": null},
        {"name": "Heavy Longbow", "type": "Ranged", "damage": 34, "element": null, "Cost": 55, "Durability": 70, "special_ability": null},
        {"name": "Silvered Bow", "type": "Ranged", "damage": 26, "element": null, "Cost": 42, "Durability": 60, "special_ability": null},
        {"name": "Crossbow Pistol", "type": "Ranged", "damage": 20, "element": null, "Cost": 40, "Durability": 50, "special_ability": null},
        {"name": "Dragon Bone Bow", "type": "Ranged", "damage": 50, "element": null, "Cost": 100, "Durability": 120, "special_ability": null},
        {"name": "Dragon Bone Crossbow", "type": "Ranged", "damage": 55, "element": null, "Cost": 120, "Durability": 130, "special_ability": null}
    ],

    "magic_items" : [
    {"name": "Fire Staff", "type": "Magic", "damage": 18, "mana_cost": 12, "element": "Fire", "Cost": 35, "Durability": 80, "special_ability": "Burn (Deals 5 Fire Damage over 3 turns)"},
    {"name": "Ice Wand", "type": "Magic", "damage": 15, "mana_cost": 10, "element": "Ice", "Cost": 28, "Durability": 70, "special_ability": "Freeze (Slows the target’s movement speed by 50% for 2 turns)"},
    {"name": "Lightning Rod", "type": "Magic", "damage": 22, "mana_cost": 15, "element": "Lightning", "Cost": 50, "Durability": 90, "special_ability": "Chain Lightning (Hits up to 3 additional targets with 10 damage each)"},
    {"name": "Death Scythe", "type": "Magic", "damage": 25, "mana_cost": 18, "element": "Death", "Cost": 55, "Durability": 100, "special_ability": "Soul Drain (Steals 5 HP from the enemy and heals the user)"},
    {"name": "Wind Blade", "type": "Magic", "damage": 20, "mana_cost": 14, "element": "Wind", "Cost": 40, "Durability": 85, "special_ability": "Gale Force (Increases the user’s attack speed by 30% for 2 turns)"},
    {"name": "Earth Hammer", "type": "Magic", "damage": 24, "mana_cost": 17, "element": "Earth", "Cost": 45, "Durability": 75, "special_ability": "Quake (Stuns the target for 1 turn and deals 5 Earth Damage)"},
    {"name": "Light Bracer", "type": "Magic", "damage": 18, "mana_cost": 10, "element": "Light", "Cost": 30, "Durability": 80, "special_ability": "Radiance (Heals the user for 10 HP and increases defense by 10% for 2 turns)"},
    {"name": "Shadow Dagger", "type": "Magic", "damage": 21, "mana_cost": 13, "element": "Shadow", "Cost": 42, "Durability": 60, "special_ability": "Shadow Strike (Increases critical hit chance by 50% for 1 turn)"},
    {"name": "Frostbow", "type": "Magic", "damage": 19, "mana_cost": 12, "element": "Ice", "Cost": 38, "Durability": 78, "special_ability": "Chill (Reduces enemy defense by 5 and slows movement by 20% for 3 turns)"}
    ]
}
